{
  "tiers": [
    {
      "id": "phase-1",
      "name": "Phase I: Diagnostic EKG",
      "tagline": "Emerging Cohesion",
      "term": "90 Days",
      "features": [
        "Commercial EKG (250+ point Revenue Journey Rubric)",
        "Perimeter Architecture (2 social Signal Nodes)",
        "Gateway Microsite (friction-free intent routing)",
        "Digital Sales Channel (Authority Engine)",
        "Custom CRM eliminating Manual Entry Tax",
        "O2O Entry Points (signatures, cards, lead magnets)",
        "Reclaim 15+ hours/week of administrative waste"
      ],
      "locked_features": [
        "Phase II: Engine Orchestration",
        "Phase III: Unified Engine"
      ],
      "cta_text": "Schedule Discovery",
      "highlighted": false
    },
    {
      "id": "phase-2",
      "name": "Phase II: Engine Orchestration",
      "tagline": "Orchestrated Cohesion — Recommended",
      "term": "6 Months",
      "features": [
        "Everything in Phase I",
        "Managed Nervous System (MNS) installation",
        "Information Fusion via Clarity + Google Tags",
        "4 Siloed Gateway Microsites for ad campaigns",
        "90-Day Content Calendar & Operational Cadence",
        "Lead Nurture & Reputation Management automation",
        "Real-time Situation Awareness dashboard"
      ],
      "locked_features": [
        "Phase III: Unified Engine"
      ],
      "cta_text": "Apply for Partnership",
      "highlighted": true
    },
    {
      "id": "phase-3",
      "name": "Phase III: Unified Engine",
      "tagline": "Commercial Sovereignty",
      "term": "12 Months",
      "features": [
        "Everything in Phase II",
        "Sovereign Engine proof-of-concept deployment",
        "Migration to proprietary managed hosting",
        "Frankenstein Stack rationalization (replace legacy vendors)",
        "Custom Architecture for CPQ/Billing",
        "The Alabrida Bridge handoff preparation",
        "Full path to Commercial Sovereignty"
      ],
      "locked_features": [],
      "cta_text": "Request Architecture Review",
      "highlighted": false
    }
  ]
}
